{
  "annotations": {
    "list": [
      {
        "builtIn": 1,
        "datasource": "-- Grafana --",
        "enable": true,
        "hide": true,
        "iconColor": "rgba(0, 211, 255, 1)",
        "name": "Annotations & Alerts",
        "type": "dashboard"
      }
    ]
  },
  "editable": true,
  "gnetId": null,
  "graphTooltip": 0,
  "id": 1,
  "links": [],
  "panels": [
    {
      "datasource": "influxdb",
      "description": "",
      "gridPos": {
        "h": 8,
        "w": 11,
        "x": 0,
        "y": 0
      },
      "id": 2,
      "options": {
        "fieldOptions": {
          "calcs": [
            "last"
          ],
          "defaults": {
			"decimals": 2,
            "mappings": [],
            "max": 45,
            "min": -15,
            "thresholds": [
              {
                "color": "purple",
                "value": null
              },
              {
                "color": "blue",
                "value": 2
              },
              {
                "color": "green",
                "value": 15
              },
              {
                "color": "yellow",
                "value": 22
              },
              {
                "color": "red",
                "value": 28
              }
            ],
            "title": ""
          },
          "override": {},
          "values": false
        },
        "orientation": "auto",
        "showThresholdLabels": false,
        "showThresholdMarkers": true
      },
      "pluginVersion": "6.5.0",
      "targets": [
        {
          "groupBy": [
            {
              "params": [
                "$__interval"
              ],
              "type": "time"
            },
            {
              "params": [
                "null"
              ],
              "type": "fill"
            }
          ],
          "orderByTime": "ASC",
          "policy": "default",
          "query": "SELECT temperature FROM dht11",
          "rawQuery": true,
          "refId": "A",
          "resultFormat": "time_series",
          "select": [
            [
              {
                "params": [
                  "value"
                ],
                "type": "field"
              },
              {
                "params": [],
                "type": "last"
              }
            ]
          ],
          "tags": []
        }
      ],
      "timeFrom": null,
      "timeShift": null,
      "title": "Temperature",
      "type": "gauge"
    },
    {
      "datasource": "influxdb",
      "gridPos": {
        "h": 8,
        "w": 12,
        "x": 12,
        "y": 0
      },
      "id": 4,
      "options": {
        "fieldOptions": {
          "calcs": [
            "last"
          ],
          "defaults": {
			"decimals": 2,
            "mappings": [],
            "max": 100,
            "min": 0,
            "thresholds": [
              {
                "color": "super-light-red",
                "value": null
              },
              {
                "color": "super-light-yellow",
                "value": 40
              },
              {
                "color": "super-light-blue",
                "value": 80
              }
            ]
          },
          "override": {},
          "values": false
        },
        "orientation": "auto",
        "showThresholdLabels": false,
        "showThresholdMarkers": true
      },
      "pluginVersion": "6.5.0",
      "targets": [
        {
          "groupBy": [
            {
              "params": [
                "$__interval"
              ],
              "type": "time"
            },
            {
              "params": [
                "null"
              ],
              "type": "fill"
            }
          ],
          "orderByTime": "ASC",
          "policy": "default",
          "query": "SELECT humidity FROM dht11",
          "rawQuery": true,
          "refId": "A",
          "resultFormat": "time_series",
          "select": [
            [
              {
                "params": [
                  "value"
                ],
                "type": "field"
              },
              {
                "params": [],
                "type": "last"
              }
            ]
          ],
          "tags": []
        }
      ],
      "timeFrom": null,
      "timeShift": null,
      "title": "Humidity",
      "type": "gauge"
    }
  ],
  "refresh": "5s",
  "schemaVersion": 21,
  "style": "dark",
  "tags": [],
  "templating": {
    "list": []
  },
  "time": {
    "from": "now-6h",
    "to": "now"
  },
  "timepicker": {},
  "timezone": "",
  "title": "SIPRI Dashboard",
  "uid": "a1b2c3d4-e5f6-g7h8-i9j0-k1l2m3n4o5p6",
  "version": 1
}
